steam_proton_helper.py
steam_proton_helper_gui.py
gui/__init__.py
gui/main_window.py
gui/widgets/__init__.py
gui/widgets/checks_panel.py
gui/widgets/fix_dialog.py
gui/widgets/proton_panel.py
gui/widgets/protondb_panel.py
gui/widgets/summary_panel.py
gui/workers/__init__.py
gui/workers/check_worker.py
gui/workers/proton_worker.py
steam_proton_helper-2.3.3.dist-info/licenses/LICENSE
steam_proton_helper-2.3.3.dist-info/METADATA
steam_proton_helper-2.3.3.dist-info/WHEEL
steam_proton_helper-2.3.3.dist-info/entry_points.txt
steam_proton_helper-2.3.3.dist-info/top_level.txt
steam_proton_helper-2.3.3.dist-info/RECORD
