Metadata-Version: 2.4
Name: steam-proton-helper
Version: 2.3.3
Summary: A comprehensive Linux tool to help setup Steam and Proton for gaming
Home-page: https://github.com/AreteDriver/SteamProtonHelper
Author: SteamProtonHelper Contributors
License-Expression: MIT
Project-URL: Homepage, https://github.com/AreteDriver/SteamProtonHelper
Project-URL: Documentation, https://github.com/AreteDriver/SteamProtonHelper#readme
Project-URL: Repository, https://github.com/AreteDriver/SteamProtonHelper
Project-URL: Bug Tracker, https://github.com/AreteDriver/SteamProtonHelper/issues
Keywords: steam,proton,linux,gaming,wine,vulkan
Classifier: Development Status :: 5 - Production/Stable
Classifier: Intended Audience :: End Users/Desktop
Classifier: Topic :: Games/Entertainment
Classifier: Topic :: System :: Installation/Setup
Classifier: Programming Language :: Python :: 3
Classifier: Programming Language :: Python :: 3.8
Classifier: Programming Language :: Python :: 3.9
Classifier: Programming Language :: Python :: 3.10
Classifier: Programming Language :: Python :: 3.11
Classifier: Programming Language :: Python :: 3.12
Classifier: Programming Language :: Python :: 3.13
Classifier: Operating System :: POSIX :: Linux
Classifier: Environment :: Console
Requires-Python: >=3.8
License-File: LICENSE
Provides-Extra: dev
Requires-Dist: pytest>=7.0; extra == "dev"
Requires-Dist: pytest-timeout>=2.0; extra == "dev"
Provides-Extra: gui
Requires-Dist: PyQt6>=6.4.0; extra == "gui"
Dynamic: home-page
Dynamic: license-file
Dynamic: requires-python
